d2dcnWidget/__init__.py
d2dcnWidget/d2dcnGUI.py
d2dcnWidget/d2dcnWidget.py
d2dcnWidget-0.2.0.dist-info/LICENSE
d2dcnWidget-0.2.0.dist-info/METADATA
d2dcnWidget-0.2.0.dist-info/WHEEL
d2dcnWidget-0.2.0.dist-info/entry_points.txt
d2dcnWidget-0.2.0.dist-info/top_level.txt
d2dcnWidget-0.2.0.dist-info/RECORD
