Metadata-Version: 2.1
Name: d2dcnWidget
Version: 0.2.0
Summary: UNKNOWN
Home-page: https://github.com/qeyup/d2dcnWidget-python
Author: Javier Moreno Garcia
Author-email: jgmore@gmail.com
License: UNKNOWN
Platform: UNKNOWN
Requires-Dist: PyQt5
Requires-Dist: d2dcn (>=0.5.1)
